filter_chatgpt_annotator/__init__.py
filter_chatgpt_annotator/filter.py
filter_chatgpt_annotator-0.1.1.dist-info/licenses/LICENSE
filter_chatgpt_annotator-0.1.1.dist-info/METADATA
filter_chatgpt_annotator-0.1.1.dist-info/WHEEL
filter_chatgpt_annotator-0.1.1.dist-info/top_level.txt
filter_chatgpt_annotator-0.1.1.dist-info/RECORD
